README.rst
setup.cfg
setup.py
django_uncertainty.egg-info/PKG-INFO
django_uncertainty.egg-info/SOURCES.txt
django_uncertainty.egg-info/dependency_links.txt
django_uncertainty.egg-info/top_level.txt
uncertainty/__init__.py
uncertainty/behaviours.py
uncertainty/conditions.py
uncertainty/middleware.py