Metadata-Version: 1.1
Name: django-uncertainty
Version: 1.6
Summary: A Django middleware to generate predictable errors on sites
Home-page: https://github.com/abarto/django_uncertainty
Author: Agustin Barto
Author-email: abarto@gmail.com
License: BSD
Platform: UNKNOWN
Classifier: Development Status :: 4 - Beta
Classifier: Environment :: Web Environment
Classifier: Framework :: Django
Classifier: Intended Audience :: Developers
Classifier: License :: OSI Approved :: MIT License
Classifier: Operating System :: OS Independent
Classifier: Programming Language :: Python
Classifier: Programming Language :: Python :: 3
Classifier: Topic :: Utilities
